zhulong4/__init__.py
zhulong4/a_b/__init__.py
zhulong4/a_b/b2b_10086_cn.py
zhulong4/a_b/b2bcoal_crp_net_cn.py
zhulong4/a_b/baowu_ouyeelbuy_com.py
zhulong4/a_b/bid_ansteel_cn.py
zhulong4/a_b/bid_powerchina_cn.py
zhulong4/a_b/bidding_ceiec_com_cn.py
zhulong4/a_b/bidding_crmsc_com_cn.py
zhulong4/a_b/buy_cnooc_com_cn.py
zhulong4/a_b/task.py
zhulong4/c_d/__init__.py
zhulong4/c_d/caigou_ceair_com.py
zhulong4/c_d/csbidding_csair_com.py
zhulong4/c_d/dfqcgs_dlzb_com.py
zhulong4/c_d/dzzb_ciesco_com_cn.py
zhulong4/c_d/task.py
zhulong4/e_f/__init__.py
zhulong4/e_f/ebid_aecc_mall_com.py
zhulong4/e_f/ec1_mcc_com_cn.py
zhulong4/e_f/ec_ccccltd_cn.py
zhulong4/e_f/ec_ceec_net_cn.py
zhulong4/e_f/ec_chalieco_com.py
zhulong4/e_f/ecp_cgnpc_com_cn.py
zhulong4/e_f/ecp_sgcc_com_cn.py
zhulong4/e_f/epp_ctg_com_cn.py
zhulong4/e_f/eps_sdic_com_cn.py
zhulong4/e_f/etp_fawiec_com.py
zhulong4/e_f/task.py
zhulong4/f_v/__init__.py
zhulong4/f_v/fwgs_sinograin_com_cn.py
zhulong4/f_v/gs_coscoshipping_com.py
zhulong4/f_v/jzcg_cfhi_com.py
zhulong4/f_v/srm_crland_com_cn.py
zhulong4/f_v/syhggs_dlzb_com.py
zhulong4/f_v/sytrq_dlzb_com.py
zhulong4/f_v/task.py
zhulong4/f_v/thzb_crsc_cn.py
zhulong4/f_v/uat_ec_chng_com_cn.py
zhulong4/util/__init__.py
zhulong4/util/cfg_db
zhulong4/util/conf.py
zhulong4/util/etl.py
zhulong4/util/fake_useragent.py
zhulong4/util/test.py
zhulong4/w_z/__init__.py
zhulong4/w_z/task.py
zhulong4/w_z/wzcgzs_95306_cn.py
zhulong4/w_z/ysky_dlzb_com.py
zhulong4/w_z/zb_crlintex_com.py
zhulong4/w_z/zgdxjt_dlzb_com.py
zhulong4/w_z/zgdzxx_dlzb_com.py
zhulong4/w_z/zghkgy_dlzb_com.py
zhulong4/w_z/zghkyl_dlzb_com.py
zhulong4/w_z/zgyy_dlzb_com.py
zhulong4/w_z/zljt_dlzb_com.py
zhulong4/www_a_c/__init__.py
zhulong4/www_a_c/task.py
zhulong4/www_a_c/www_bidding_csg_cn.py
zhulong4/www_a_c/www_cdt_eb_com.py
zhulong4/www_a_c/www_cgdcbidding_com.py
zhulong4/www_a_c/www_chdtp_com.py
zhulong4/www_a_c/www_china_tender_com_cn.py
zhulong4/www_a_c/www_chinabidding_com.py
zhulong4-5.3.24.dist-info/METADATA
zhulong4-5.3.24.dist-info/WHEEL
zhulong4-5.3.24.dist-info/top_level.txt
zhulong4-5.3.24.dist-info/RECORD
